multipca/__init__.py
multipca/plot.py
multipca/solver.py
multipca/data/citibike_data.npy
multipca-0.1.2.dist-info/licenses/LICENSE
multipca-0.1.2.dist-info/METADATA
multipca-0.1.2.dist-info/WHEEL
multipca-0.1.2.dist-info/top_level.txt
multipca-0.1.2.dist-info/RECORD
