Metadata-Version: 2.4
Name: multipca
Version: 0.1.2
Summary: A package for multiPCA
Author-email: Jialin Ouyang <jo2559@columbia.edu>
License: MIT
Project-URL: Homepage, https://github.com/j-bagel/multipca
Requires-Python: >=3.9
License-File: LICENSE
Requires-Dist: numpy>=1.24
Requires-Dist: scipy>=1.5
Requires-Dist: matplotlib>=3.6
Dynamic: license-file
